asynchronousfilereader/__init__.py
asynchronousfilereader/demo.py
asynchronousfilereader-0.2.1.dist-info/DESCRIPTION.rst
asynchronousfilereader-0.2.1.dist-info/METADATA
asynchronousfilereader-0.2.1.dist-info/metadata.json
asynchronousfilereader-0.2.1.dist-info/RECORD
asynchronousfilereader-0.2.1.dist-info/top_level.txt
asynchronousfilereader-0.2.1.dist-info/WHEEL
